pyticle/__init__.py
pyticle/__main__.py
pyticle/benchmark.py
pyticle/data_visualizer.py
pyticle/demo_run.py
pyticle/particle.py
pyticle/swarm_optimization.py
pyticle-0.0.3.dist-info/LICENSE
pyticle-0.0.3.dist-info/METADATA
pyticle-0.0.3.dist-info/WHEEL
pyticle-0.0.3.dist-info/top_level.txt
pyticle-0.0.3.dist-info/RECORD
