Metadata-Version: 2.1
Name: pyticle
Version: 0.0.3
Summary: A Python Library for Particle Swarm Intelligence
Home-page: https://github.com/owhadi/pyticle
Author: Moein Owhadi Kareshk
Author-email: moein.owhadi@gmail.com
License: UNKNOWN
Platform: UNKNOWN
Classifier: Programming Language :: Python :: 3
Classifier: License :: OSI Approved :: MIT License
Classifier: Operating System :: OS Independent
Requires-Python: >=3.6
Requires-Dist: numpy (~=1.19.1)
Requires-Dist: imageio (~=2.9.0)
Requires-Dist: matplotlib (~=3.3.0)
Requires-Dist: joblib (~=0.16.0)
Requires-Dist: setuptools (~=49.2.0)
Requires-Dist: pytest
